{
    "loai": "y_te", 
    "nguon": "viettan.org", 
    "link": "https://viettan.org/tai-sao-sai-gon/", 
    "tg_dang_tin": "2021-09-05 00:00:00", 
    "tieu_de": "Tại sao Sài Gòn?", 
    "noi_dung": "Mấy bạn tôi ở Hà Nội gọi điện thăm hỏi và cứ lo lắng cho Sài Gòn. Rồi lại bảo tôi giải đáp cho những thắc mắc băn khoăn. Đại thể có mấy vấn đề. 1. Dân Sài Gòn có vẻ kém kỷ luật, tập trung đông, làm bùng phát mạnh Covid -19? 2. Sao tỉ lệ tử vong vì Covid -19 ở Sài Gòn cao vậy? 3. Phong trào làm từ thiện ở Sài Gòn rầm rộ quá, nhưng có thực chất không? 4. Bây giờ chống Covid ở Sài Gòn liệu có hy vọng cải thiện gì chưa? © Copyright 2020 | Đảng Việt Tân", 
    "nhan": 1
}