{
    "loai": "y_te", 
    "nguon": "danlambaovn.blogspot.com", 
    "link": "https://danlambaovn.blogspot.com/2021/07/phat-dan-theo-chi-tieu.html", 
    "tg_dang_tin": "2021-07-14 11:26:00", 
    "tieu_de": "Phạt dân theo chỉ tiêu",
    "noi_dung": "Bạn đọc Danlambao - Mới đây, mạng xã hội tại Việt Nam lan truyền một văn bản của nhà cầm quyền phường 6, quận Gò Vấp về phân công nhiệm vụ phòng, chống dịch Covid-19 trong thời gian thực hiện phong toả theo chỉ thị 16.  Theo văn bản này, “hàng ngày, tổ chức 1 chốt xử phạt trước cổng cơ quan UBND phường. Mỗi ca phải phạt 20 trường hợp”; Và “Tổ tuần tra, giám sát hoạt động cả tuần, \"mỗi ca phạt 5 trường hợp”.   Trao đổi với báo chí, ông Phan đình An, Chủ tịch phường 6 xác nhận nội dung trên là một phần thông báo phân công nhiệm vụ phòng chống dịch của phường này.  Ngoài ra, ông Nguyễn Trí Dũng, Chủ tịch quận Gò Vấp cũng xác nhận, văn bản lan truyền trên là “thông báo phân công nội bộ công việc trong đơn vị”.  Việc phạt dân theo chỉ tiêu trong thời điểm dịch đang bùng phát nghiêm trọng đã tạo ra nhiều ý kiến chỉ trích trong dư luận.  Sau khi bị lan truyền trên mạng xã hội, Chủ tịch phường 6 đã ngay lập tức có văn bản điều chỉnh việc phân công nhiệm vụ. Theo đó, tổ trực hành chính phản ứng nhanh và tổ tuần tra, giám sát địa bàn sẽ tiến hành xử phạt tất các trường hợp vi phạm quy định phòng, chống dịch khi kiểm tra phát hiện thay vì đưa chỉ tiêu.  Bạn đọc Danlambao danlambaovn.blogspot.com", 
    "nhan": 1
}